{"web":{"client_id":"739048140415-eqg592sf2j7rlu0ds96q15v7ihdfrkoh.apps.googleusercontent.com","project_id":"bustling-tuner-128806","auth_uri":"https://accounts.google.com/o/oauth2/auth","token_uri":"https://accounts.google.com/o/oauth2/token","auth_provider_x509_cert_url":"https://www.googleapis.com/oauth2/v1/certs","client_secret":"kl2wJep68QRhy3nQFs5hAV7i","redirect_uris":["http://localhost:3000/google_apis/people_callback","http://localhost:3000/google_apis/contacts_callback"],"javascript_origins":["http://localhost:3000"]}}
